melodica_notes/__init__.py
melodica_notes/chords.py
melodica_notes/cli.py
melodica_notes/harmonics.py
melodica_notes/scales.py
melodica_notes-0.1.1.dist-info/LICENSE
melodica_notes-0.1.1.dist-info/METADATA
melodica_notes-0.1.1.dist-info/WHEEL
melodica_notes-0.1.1.dist-info/entry_points.txt
melodica_notes-0.1.1.dist-info/RECORD
