Metadata-Version: 2.1
Name: melodica-notes
Version: 0.1.1
Summary: Melodica Notes is a CLI tool to assist melodica players with musical scales, chords, and harmonics.
License: GNU GPLv3
Author: Victor Senna
Author-email: vhsenna@gmail.com
Requires-Python: >=3.10,<4.0
Classifier: Development Status :: 5 - Production/Stable
Classifier: Environment :: Console
Classifier: License :: Other/Proprietary License
Classifier: Natural Language :: English
Classifier: Programming Language :: Python :: 3
Classifier: Programming Language :: Python :: 3.10
Classifier: Programming Language :: Python :: 3.11
Classifier: Programming Language :: Python :: 3.12
Classifier: Topic :: Education
Requires-Dist: rich (>=13.7.1,<14.0.0)
Requires-Dist: typer (>=0.12.3,<0.13.0)
Project-URL: Documentation, https://melodica-notes.readthedocs.io
Project-URL: Donate, https://www.paypal.com/donate/?hosted_button_id=U37WUXE2TSW6Y
Project-URL: Issue Tracker, https://github.com/vhsenna/melodica-notes/issues
Project-URL: Source, https://github.com/vhsenna/melodica-notes
